Workbook

Sheet Dashboard
A1: Sales performance — September 2026
A2: Set the three filters, and every card, chart and table on this page follows.
A4: Region | G4: Product | M4: Salesperson | S4: Click a yellow cell and use its dropdown. “All” clears that filter.
A5: All | G5: All | M5: All
A7: Revenue | G7: Units sold | M7: Transactions | S7: Average order value
A8: =SUMIFS(Data!$G$2:$G$11,Data!$H$2:$H$11,1) -> 3689000 | G8: =SUMIFS(Data!$E$2:$E$11,Data!$H$2:$H$11,1) -> 70 | M8: =COUNTIFS(Data!$H$2:$H$11,1) -> 10 | S8: =IFERROR(A8/M8,0) -> 368900
A10: Quantity x unit price, filtered | G10: Items moved in the selection | M10: Sales lines in the selection | S10: Revenue per transaction
A12: Share of period total | G12: Top product | M12: Top salesperson | S12: Best day
A13: =IFERROR(A8/Data!$G$12,0) -> 1 | G13: =IF($A$8=0,"—",INDEX($A$50:$A$53,MATCH(MAX($B$50:$B$53),$B$50:$B$53,0))) -> Laptop | M13: =IF($A$8=0,"—",INDEX($M$50:$M$52,MATCH(MAX($N$50:$N$52),$N$50:$N$52,0))) -> David | S13: =IF($A$8=0,"—",INDEX($S$50:$S$59,MATCH(MAX($T$50:$T$59),$T$50:$T$59,0))) -> 46266
A15: Against ₦3,689,000 for 1–10 Sept | G15: Largest revenue line | M15: Most revenue closed | S15: Highest single-day revenue
A48: Revenue by product | G48: Revenue by region | M48: Revenue by salesperson | S48: Revenue by day
A49: Product | B49: Revenue | C49: Units | D49: Deals | G49: Region | H49: Revenue | I49: Units | J49: Deals | M49: Salesperson | N49: Revenue | O49: Units | P49: Deals | S49: Date | T49: Revenue | U49: Units | V49: Deals
A50: Laptop | B50: =SUMIFS(Data!$G$2:$G$11,Data!$H$2:$H$11,1,Data!$B$2:$B$11,$A50) -> 2250000 | C50: =SUMIFS(Data!$E$2:$E$11,Data!$H$2:$H$11,1,Data!$B$2:$B$11,$A50) -> 5 | D50: =COUNTIFS(Data!$H$2:$H$11,1,Data!$B$2:$B$11,$A50) -> 3 | G50: Lagos | H50: =SUMIFS(Data!$G$2:$G$11,Data!$H$2:$H$11,1,Data!$C$2:$C$11,$G50) -> 1734000 | I50: =SUMIFS(Data!$E$2:$E$11,Data!$H$2:$H$11,1,Data!$C$2:$C$11,$G50) -> 31 | J50: =COUNTIFS(Data!$H$2:$H$11,1,Data!$C$2:$C$11,$G50) -> 4 | M50: David | N50: =SUMIFS(Data!$G$2:$G$11,Data!$H$2:$H$11,1,Data!$D$2:$D$11,$M50) -> 2085000 | O50: =SUMIFS(Data!$E$2:$E$11,Data!$H$2:$H$11,1,Data!$D$2:$D$11,$M50) -> 7 | P50: =COUNTIFS(Data!$H$2:$H$11,1,Data!$D$2:$D$11,$M50) -> 3 | S50: =Data!$A$2 -> 46266 | T50: =SUMIFS(Data!$G$2:$G$11,Data!$H$2:$H$11,1,Data!$A$2:$A$11,$S50) -> 900000 | U50: =SUMIFS(Data!$E$2:$E$11,Data!$H$2:$H$11,1,Data!$A$2:$A$11,$S50) -> 2 | V50: =COUNTIFS(Data!$H$2:$H$11,1,Data!$A$2:$A$11,$S50) -> 1
A51: Monitor | B51: =SUMIFS(Data!$G$2:$G$11,Data!$H$2:$H$11,1,Data!$B$2:$B$11,$A51) -> 665000 | C51: =SUMIFS(Data!$E$2:$E$11,Data!$H$2:$H$11,1,Data!$B$2:$B$11,$A51) -> 7 | D51: =COUNTIFS(Data!$H$2:$H$11,1,Data!$B$2:$B$11,$A51) -> 2 | G51: Ogun | H51: =SUMIFS(Data!$G$2:$G$11,Data!$H$2:$H$11,1,Data!$C$2:$C$11,$G51) -> 785000 | I51: =SUMIFS(Data!$E$2:$E$11,Data!$H$2:$H$11,1,Data!$C$2:$C$11,$G51) -> 17 | J51: =COUNTIFS(Data!$H$2:$H$11,1,Data!$C$2:$C$11,$G51) -> 3 | M51: Sarah | N51: =SUMIFS(Data!$G$2:$G$11,Data!$H$2:$H$11,1,Data!$D$2:$D$11,$M51) -> 954000 | O51: =SUMIFS(Data!$E$2:$E$11,Data!$H$2:$H$11,1,Data!$D$2:$D$11,$M51) -> 39 | P51: =COUNTIFS(Data!$H$2:$H$11,1,Data!$D$2:$D$11,$M51) -> 4 | S51: =Data!$A$3 -> 46267 | T51: =SUMIFS(Data!$G$2:$G$11,Data!$H$2:$H$11,1,Data!$A$2:$A$11,$S51) -> 120000 | U51: =SUMIFS(Data!$E$2:$E$11,Data!$H$2:$H$11,1,Data!$A$2:$A$11,$S51) -> 10 | V51: =COUNTIFS(Data!$H$2:$H$11,1,Data!$A$2:$A$11,$S51) -> 1
A52: Keyboard | B52: =SUMIFS(Data!$G$2:$G$11,Data!$H$2:$H$11,1,Data!$B$2:$B$11,$A52) -> 234000 | C52: =SUMIFS(Data!$E$2:$E$11,Data!$H$2:$H$11,1,Data!$B$2:$B$11,$A52) -> 13 | D52: =COUNTIFS(Data!$H$2:$H$11,1,Data!$B$2:$B$11,$A52) -> 2 | G52: Oyo | H52: =SUMIFS(Data!$G$2:$G$11,Data!$H$2:$H$11,1,Data!$C$2:$C$11,$G52) -> 1170000 | I52: =SUMIFS(Data!$E$2:$E$11,Data!$H$2:$H$11,1,Data!$C$2:$C$11,$G52) -> 22 | J52: =COUNTIFS(Data!$H$2:$H$11,1,Data!$C$2:$C$11,$G52) -> 3 | M52: James | N52: =SUMIFS(Data!$G$2:$G$11,Data!$H$2:$H$11,1,Data!$D$2:$D$11,$M52) -> 650000 | O52: =SUMIFS(Data!$E$2:$E$11,Data!$H$2:$H$11,1,Data!$D$2:$D$11,$M52) -> 24 | P52: =COUNTIFS(Data!$H$2:$H$11,1,Data!$D$2:$D$11,$M52) -> 3 | S52: =Data!$A$4 -> 46268 | T52: =SUMIFS(Data!$G$2:$G$11,Data!$H$2:$H$11,1,Data!$A$2:$A$11,$S52) -> 90000 | U52: =SUMIFS(Data!$E$2:$E$11,Data!$H$2:$H$11,1,Data!$A$2:$A$11,$S52) -> 5 | V52: =COUNTIFS(Data!$H$2:$H$11,1,Data!$A$2:$A$11,$S52) -> 1
A53: Mouse | B53: =SUMIFS(Data!$G$2:$G$11,Data!$H$2:$H$11,1,Data!$B$2:$B$11,$A53) -> 540000 | C53: =SUMIFS(Data!$E$2:$E$11,Data!$H$2:$H$11,1,Data!$B$2:$B$11,$A53) -> 45 | D53: =COUNTIFS(Data!$H$2:$H$11,1,Data!$B$2:$B$11,$A53) -> 3 | G53: Total | H53: =SUM(H50:H52) -> 3689000 | I53: =SUM(I50:I52) -> 70 | J53: =SUM(J50:J52) -> 10 | M53: Total | N53: =SUM(N50:N52) -> 3689000 | O53: =SUM(O50:O52) -> 70 | P53: =SUM(P50:P52) -> 10 | S53: =Data!$A$5 -> 46269 | T53: =SUMIFS(Data!$G$2:$G$11,Data!$H$2:$H$11,1,Data!$A$2:$A$11,$S53) -> 450000 | U53: =SUMIFS(Data!$E$2:$E$11,Data!$H$2:$H$11,1,Data!$A$2:$A$11,$S53) -> 1 | V53: =COUNTIFS(Data!$H$2:$H$11,1,Data!$A$2:$A$11,$S53) -> 1
A54: Total | B54: =SUM(B50:B53) -> 3689000 | C54: =SUM(C50:C53) -> 70 | D54: =SUM(D50:D53) -> 10 | S54: =Data!$A$6 -> 46270 | T54: =SUMIFS(Data!$G$2:$G$11,Data!$H$2:$H$11,1,Data!$A$2:$A$11,$S54) -> 285000 | U54: =SUMIFS(Data!$E$2:$E$11,Data!$H$2:$H$11,1,Data!$A$2:$A$11,$S54) -> 3 | V54: =COUNTIFS(Data!$H$2:$H$11,1,Data!$A$2:$A$11,$S54) -> 1
S55: =Data!$A$7 -> 46271 | T55: =SUMIFS(Data!$G$2:$G$11,Data!$H$2:$H$11,1,Data!$A$2:$A$11,$S55) -> 180000 | U55: =SUMIFS(Data!$E$2:$E$11,Data!$H$2:$H$11,1,Data!$A$2:$A$11,$S55) -> 15 | V55: =COUNTIFS(Data!$H$2:$H$11,1,Data!$A$2:$A$11,$S55) -> 1
S56: =Data!$A$8 -> 46272 | T56: =SUMIFS(Data!$G$2:$G$11,Data!$H$2:$H$11,1,Data!$A$2:$A$11,$S56) -> 144000 | U56: =SUMIFS(Data!$E$2:$E$11,Data!$H$2:$H$11,1,Data!$A$2:$A$11,$S56) -> 8 | V56: =COUNTIFS(Data!$H$2:$H$11,1,Data!$A$2:$A$11,$S56) -> 1
S57: =Data!$A$9 -> 46273 | T57: =SUMIFS(Data!$G$2:$G$11,Data!$H$2:$H$11,1,Data!$A$2:$A$11,$S57) -> 380000 | U57: =SUMIFS(Data!$E$2:$E$11,Data!$H$2:$H$11,1,Data!$A$2:$A$11,$S57) -> 4 | V57: =COUNTIFS(Data!$H$2:$H$11,1,Data!$A$2:$A$11,$S57) -> 1
S58: =Data!$A$10 -> 46274 | T58: =SUMIFS(Data!$G$2:$G$11,Data!$H$2:$H$11,1,Data!$A$2:$A$11,$S58) -> 900000 | U58: =SUMIFS(Data!$E$2:$E$11,Data!$H$2:$H$11,1,Data!$A$2:$A$11,$S58) -> 2 | V58: =COUNTIFS(Data!$H$2:$H$11,1,Data!$A$2:$A$11,$S58) -> 1
S59: =Data!$A$11 -> 46275 | T59: =SUMIFS(Data!$G$2:$G$11,Data!$H$2:$H$11,1,Data!$A$2:$A$11,$S59) -> 240000 | U59: =SUMIFS(Data!$E$2:$E$11,Data!$H$2:$H$11,1,Data!$A$2:$A$11,$S59) -> 20 | V59: =COUNTIFS(Data!$H$2:$H$11,1,Data!$A$2:$A$11,$S59) -> 1
S60: Total | T60: =SUM(T50:T59) -> 3689000 | U60: =SUM(U50:U59) -> 70 | V60: =SUM(V50:V59) -> 10
A62: Revenue = quantity x unit price. Average order value = revenue ÷ transactions. Empty charts or dashes mean no transaction matches the current filters.

Sheet Data
A1: Date | B1: Product | C1: Region | D1: Salesperson | E1: Quantity | F1: Unit Price | G1: Revenue | H1: In current view
A2: 46266 | B2: Laptop | C2: Lagos | D2: David | E2: 2 | F2: 450000 | G2: =E2*F2 -> 900000 | H2: =IF(AND(OR(Dashboard!$A$5="All",C2=Dashboard!$A$5),OR(Dashboard!$G$5="All",B2=Dashboard!$G$5),OR(Dashboard!$M$5="All",D2=Dashboard!$M$5)),1,0) -> 1
A3: 46267 | B3: Mouse | C3: Ogun | D3: Sarah | E3: 10 | F3: 12000 | G3: =E3*F3 -> 120000 | H3: =IF(AND(OR(Dashboard!$A$5="All",C3=Dashboard!$A$5),OR(Dashboard!$G$5="All",B3=Dashboard!$G$5),OR(Dashboard!$M$5="All",D3=Dashboard!$M$5)),1,0) -> 1
A4: 46268 | B4: Keyboard | C4: Oyo | D4: James | E4: 5 | F4: 18000 | G4: =E4*F4 -> 90000 | H4: =IF(AND(OR(Dashboard!$A$5="All",C4=Dashboard!$A$5),OR(Dashboard!$G$5="All",B4=Dashboard!$G$5),OR(Dashboard!$M$5="All",D4=Dashboard!$M$5)),1,0) -> 1
A5: 46269 | B5: Laptop | C5: Lagos | D5: Sarah | E5: 1 | F5: 450000 | G5: =E5*F5 -> 450000 | H5: =IF(AND(OR(Dashboard!$A$5="All",C5=Dashboard!$A$5),OR(Dashboard!$G$5="All",B5=Dashboard!$G$5),OR(Dashboard!$M$5="All",D5=Dashboard!$M$5)),1,0) -> 1
A6: 46270 | B6: Monitor | C6: Ogun | D6: David | E6: 3 | F6: 95000 | G6: =E6*F6 -> 285000 | H6: =IF(AND(OR(Dashboard!$A$5="All",C6=Dashboard!$A$5),OR(Dashboard!$G$5="All",B6=Dashboard!$G$5),OR(Dashboard!$M$5="All",D6=Dashboard!$M$5)),1,0) -> 1
A7: 46271 | B7: Mouse | C7: Oyo | D7: James | E7: 15 | F7: 12000 | G7: =E7*F7 -> 180000 | H7: =IF(AND(OR(Dashboard!$A$5="All",C7=Dashboard!$A$5),OR(Dashboard!$G$5="All",B7=Dashboard!$G$5),OR(Dashboard!$M$5="All",D7=Dashboard!$M$5)),1,0) -> 1
A8: 46272 | B8: Keyboard | C8: Lagos | D8: Sarah | E8: 8 | F8: 18000 | G8: =E8*F8 -> 144000 | H8: =IF(AND(OR(Dashboard!$A$5="All",C8=Dashboard!$A$5),OR(Dashboard!$G$5="All",B8=Dashboard!$G$5),OR(Dashboard!$M$5="All",D8=Dashboard!$M$5)),1,0) -> 1
A9: 46273 | B9: Monitor | C9: Ogun | D9: James | E9: 4 | F9: 95000 | G9: =E9*F9 -> 380000 | H9: =IF(AND(OR(Dashboard!$A$5="All",C9=Dashboard!$A$5),OR(Dashboard!$G$5="All",B9=Dashboard!$G$5),OR(Dashboard!$M$5="All",D9=Dashboard!$M$5)),1,0) -> 1
A10: 46274 | B10: Laptop | C10: Oyo | D10: David | E10: 2 | F10: 450000 | G10: =E10*F10 -> 900000 | H10: =IF(AND(OR(Dashboard!$A$5="All",C10=Dashboard!$A$5),OR(Dashboard!$G$5="All",B10=Dashboard!$G$5),OR(Dashboard!$M$5="All",D10=Dashboard!$M$5)),1,0) -> 1
A11: 46275 | B11: Mouse | C11: Lagos | D11: Sarah | E11: 20 | F11: 12000 | G11: =E11*F11 -> 240000 | H11: =IF(AND(OR(Dashboard!$A$5="All",C11=Dashboard!$A$5),OR(Dashboard!$G$5="All",B11=Dashboard!$G$5),OR(Dashboard!$M$5="All",D11=Dashboard!$M$5)),1,0) -> 1
A12: TOTAL | E12: =SUM(E2:E11) -> 70 | G12: =SUM(G2:G11) -> 3689000 | H12: =SUM(H2:H11) -> 10
A14: How to read this sheet
A15: Blue cells are the source data you type in; black cells are formulas — Revenue = Quantity x Unit Price.
A16: “In current view” returns 1 when a row passes the three dropdown filters on the Dashboard, 0 when it does not.
A17: Every card, table and chart on the Dashboard reads this column, so one dropdown change updates the whole page.
A18: Source: transactions supplied by the user, 1–10 September 2026. Quantity sums to 70 units (the original table showed 66).

Sheet Lists
A1: Region | B1: Product | C1: Salesperson
A2: All | B2: All | C2: All
A3: Lagos | B3: Laptop | C3: David
A4: Ogun | B4: Monitor | C4: Sarah
A5: Oyo | B5: Keyboard | C5: James
B6: Mouse

Sheet Report
A1: Sales review — 1 to 10 September 2026
A2: These figures cover the whole period and do not move with the Dashboard filters.
A4: Headline numbers
A5: Total revenue | B5: =Data!$G$12 -> 3689000 | D5: Sum of all ten transactions.
A6: Units sold | B6: =Data!$E$12 -> 70 | D6: The ten rows add to 70; the original summary row showed 66.
A7: Transactions | B7: =COUNT(Data!$G$2:$G$11) -> 10 | D7: One line per sale.
A8: Average order value | B8: =B5/B7 -> 368900 | D8: Revenue divided by transactions.
A9: Average units per sale | B9: =B6/B7 -> 7 | D9: Pulled up by the 20-unit mouse order on 10/09.
A11: Where the revenue comes from
A12: Product | B12: Revenue | C12: Share | D12: Reading
A13: Laptop | B13: =SUMIF(Data!$B$2:$B$11,$A13,Data!$G$2:$G$11) -> 2250000 | C13: =B13/$B$5 -> 0.60992139 | D13: Three sales carry most of the period. One lost laptop deal costs more than a week of mice.
A14: Monitor | B14: =SUMIF(Data!$B$2:$B$11,$A14,Data!$G$2:$G$11) -> 665000 | C14: =B14/$B$5 -> 0.18026565 | D14: Steady mid-ticket item; both sales landed in Ogun.
A15: Keyboard | B15: =SUMIF(Data!$B$2:$B$11,$A15,Data!$G$2:$G$11) -> 234000 | C15: =B15/$B$5 -> 0.063431824 | D15: Low ticket and low volume — the weakest line on both measures.
A16: Mouse | B16: =SUMIF(Data!$B$2:$B$11,$A16,Data!$G$2:$G$11) -> 540000 | C16: =B16/$B$5 -> 0.14638113 | D16: 45 of the 70 units, but the smallest revenue share. Volume is not value here.
A18: Regions and people
A19: Group | B19: Revenue | C19: Share | D19: Reading
A20: Lagos | B20: =SUMIF(Data!$C$2:$C$11,$A20,Data!$G$2:$G$11) -> 1734000 | C20: =B20/$B$5 -> 0.47004608 | D20: Four deals and the widest product mix of the three regions.
A21: Ogun | B21: =SUMIF(Data!$C$2:$C$11,$A21,Data!$G$2:$G$11) -> 785000 | C21: =B21/$B$5 -> 0.2127948 | D21: The only region with no laptop sale, which caps its ceiling.
A22: Oyo | B22: =SUMIF(Data!$C$2:$C$11,$A22,Data!$G$2:$G$11) -> 1170000 | C22: =B22/$B$5 -> 0.31715912 | D22: Fewest deals, but one laptop sale keeps it competitive.
A23: David | B23: =SUMIF(Data!$D$2:$D$11,$A23,Data!$G$2:$G$11) -> 2085000 | C23: =B23/$B$5 -> 0.56519382 | D23: Three deals, all high-ticket — the best revenue per deal.
A24: Sarah | B24: =SUMIF(Data!$D$2:$D$11,$A24,Data!$G$2:$G$11) -> 954000 | C24: =B24/$B$5 -> 0.25860667 | D24: Most deals, but half of them are low-ticket accessories.
A25: James | B25: =SUMIF(Data!$D$2:$D$11,$A25,Data!$G$2:$G$11) -> 650000 | C25: =B25/$B$5 -> 0.17619951 | D25: Mixed basket; monitors do most of the work.
A27: What to do next
A28: Protect laptop volume. Three units out of 70 produce the largest slice of revenue, so one lost laptop deal hurts more than any accessory shortfall.
A29: Attach accessories to laptop sales. Mice and keyboards already move in volume; bundling them lifts order value without new footfall.
A30: Give Ogun a laptop push. It is the only region with no laptop sale in the period, and it already converts monitors well.
A31: Share David's approach to high-ticket deals with Sarah, whose deal count is highest but whose basket skews to accessories.
A32: Correct the source total: the quantity column sums to 70 units, not 66. Revenue of ₦3,689,000 is correct.
A35: Source: transaction list supplied by the user, 1–10 September 2026. Every figure is a formula over the Data sheet.
